cdd_context/__init__.py
cdd_context/cache.py
cdd_context/cli.py
cdd_context/generator.py
cdd_context/scanner.py
cdd_context/summarizer.py
cdd_context-0.3.1.dist-info/METADATA
cdd_context-0.3.1.dist-info/WHEEL
cdd_context-0.3.1.dist-info/entry_points.txt
cdd_context-0.3.1.dist-info/top_level.txt
cdd_context-0.3.1.dist-info/RECORD
