Metadata-Version: 2.4
Name: cdd-context
Version: 0.3.1
Summary: Generate LLM context files for codebases
Author: Gareth Dyne
License: MIT
Project-URL: Homepage, https://github.com/thegdyne/cdd-context
Project-URL: Repository, https://github.com/thegdyne/cdd-context
Project-URL: Issues, https://github.com/thegdyne/cdd-context/issues
Keywords: llm,context,claude,ai,cdd
Classifier: Development Status :: 3 - Alpha
Classifier: Intended Audience :: Developers
Classifier: License :: OSI Approved :: MIT License
Classifier: Programming Language :: Python :: 3
Classifier: Programming Language :: Python :: 3.10
Classifier: Programming Language :: Python :: 3.11
Classifier: Programming Language :: Python :: 3.12
Requires-Python: >=3.10
Requires-Dist: anthropic>=0.18.0
Provides-Extra: dev
Requires-Dist: pytest>=7.0; extra == "dev"
Requires-Dist: cdd-tooling; extra == "dev"
